{   
    "car_details": {
        "id": 1,
        "brand": "Volkswagen",
        "model": "Passat",
        "generate": "B8",
        "year_of_production": "2018",
        "mileage": "60 000",
        "displacement": "1998",
        "fuel": "diesel",
        "power": "190",
        "drive": "4x4",
        "number_of_doors": "5",
        "number_of_places": "5",
        "color": "czarny",
        "country_of_origin": "Polska",
        "first_registration": "01/05/2018",
        "car_condition": "używany",
        "description": "Sprzedam Volkswagen Passat B8, jestem jego pierwszym właścicielem. Samochód ma około 60 000 przebiegu, jest w stanie dobrym. Kupiony został w Polsce, jest w 100% bezwypadkowy. Wszystkie elementy nadwozia są w oryginalnym lakierze.",
        "images": [
            {
                "src": "https://thumbs.img-sprzedajemy.pl/1000x901c/99/a6/91/volkswagen-passat-b8-kombi-data-produkcji-22-diesel-531704361.jpg",
                "alt": "Passat B8 zdjęcie"
            },
            {
                "src": "https://bi.im-g.pl/im/d3/14/10/z16860627IER,Volkswagen-Passat-B8.jpg",
                "alt": "Passat B8 zdjęcie"
            },
            {
                "src": "https://thumbs.img-sprzedajemy.pl/1000x901c/5e/b8/09/volkswagen-passat-b8-18-tsi-180-comfortline-swiatla-led-warszawa-527498534.jpg",
                "alt": "Passat B8 zdjęcie"
            },
            {
                "src": "https://thumbs.img-sprzedajemy.pl/1000x901c/9a/92/84/volkswagen-passat-b8-18-tsi-180-comfortline-centralny-zamek-mazowieckie-warszawa-527498537.jpg",
                "alt": "Passat B8 zdjęcie"
            },
            {
                "src": "https://bi.im-g.pl/im/c9/14/10/z16860617AMP,Volkswagen-Passat-B8.jpg",
                "alt": "Passat B8 zdjęcie"
            },
            {
                "src": "https://thumbs.img-sprzedajemy.pl/1000x901c/12/de/f2/volkswagen-passat-comfortline-salon-polska-1wl-manualna-wloclawek-555476152.jpg",
                "alt": "Passat B8 zdjęcie"
            }
        ],
        "video": "https://www.youtube.com/watch?v=GbD1DwHWbp0",
        "price": "40 000",
        "to_negotiate": true
    },
    "car_equipment": ["Interfejs Bluuetooth", "Zestaw głośnomówiący", "Gniazdo USB", "System nawigacji satelitarnej", "Klimatyzacja automatyczna (dwustrefowa)", "Podłokietniki", "Kierownica ze sterowaniem radia", "Podgrzewane fotele", "Kierownica wielofunkcyjna", "Lusterka boczne ustawiane elektrycznie", "Asystent świateł drogowych","System Start/Stop", "Oświetlenie wnętrza LED", "ESP","Poduszka powietrzna kierowcy" ,"Boczna poduszka powietrzna kierowcy", "System wspomagania hamowania"]

    

}